dff_en/rtl/dff_en.sv
`timescale 1ns / 1ps
module dff_en(i_clk,
	   i_reset,
	   i_en,
	   i_input,
	   o_output);

parameter WIDTH = 64;

input i_clk;
input i_reset;
input i_en;
input [WIDTH-1:0] i_input;

output reg [WIDTH-1:0] o_output;

always_ff @ (posedge i_clk) begin
   if (i_reset) begin
	o_output <= 'b0;
   end else begin
	if (i_en) 
	    o_output <= i_input;
   end
end

endmodule

dff_en/dump.vcd
$version Generated by VerilatedVcd $end
$timescale 1ps $end
 $scope module $rootio $end
  $var wire 1 # i_clk $end
  $var wire 1 $ i_reset $end
  $var wire 1 % i_en $end
  $var wire 64 & i_input [63:0] $end
  $var wire 64 ( o_output [63:0] $end
 $upscope $end
 $scope module dff_en $end
  $var wire 32 1 WIDTH [31:0] $end
  $var wire 1 * i_clk $end
  $var wire 1 + i_reset $end
  $var wire 1 , i_en $end
  $var wire 64 - i_input [63:0] $end
  $var wire 64 / o_output [63:0] $end
 $upscope $end
$enddefinitions $end


#0
1#
0$
0%
b0000000000000000000000000000000000000000000000000000000001100100 &
b0000000000000000000000000000000000000000000000000000000000000000 (
1*
0+
0,
b0000000000000000000000000000000000000000000000000000000001100100 -
b0000000000000000000000000000000000000000000000000000000000000000 /
b00000000000000000000000001000000 1
#5000
0#
0*
#10000
1#
1%
1*
1,
#15000
0#
0*
#20000
1#
b0000000000000000000000000000000000000000000000000000000011111010 &
b0000000000000000000000000000000000000000000000000000000001100100 (
1*
b0000000000000000000000000000000000000000000000000000000011111010 -
b0000000000000000000000000000000000000000000000000000000001100100 /
#25000
0#
0*
#30000
1#
0%
b0000000000000000000000000000000000000000000000000000000001100100 &
b0000000000000000000000000000000000000000000000000000000011111010 (
1*
0,
b0000000000000000000000000000000000000000000000000000000001100100 -
b0000000000000000000000000000000000000000000000000000000011111010 /
#35000
0#
0*
#40000
1#
1%
b0000000000000000000000000000000000000000000000011000011010100000 &
1*
1,
b0000000000000000000000000000000000000000000000011000011010100000 -
#45000
0#
0*
#50000
1#
b0000000000000000000000000000000000000000000000011000011010100000 (
1*
b0000000000000000000000000000000000000000000000011000011010100000 /
#55000
0#
0*
#60000
1#
1*
#65000
0#
0*
#70000
1#
b0000000000000000000000000000000011111111111111111111111111111111 &
1*
b0000000000000000000000000000000011111111111111111111111111111111 -
#75000
0#
0*
#80000
1#
b0000000000000000000000000000000011111111111111111111111111111111 (
1*
b0000000000000000000000000000000011111111111111111111111111111111 /
#85000
0#
0*
#90000
1#
b0000000000000000000000000000000000000000000000010011011110110101 &
1*
b0000000000000000000000000000000000000000000000010011011110110101 -
#95000
0#
0*
#100000
1#
b0000000000000000000000000000000000000000000000010011011110110101 (
1*
b0000000000000000000000000000000000000000000000010011011110110101 /
